nerus/__init__.py
nerus/test.py
nerus-1.7.0.dist-info/METADATA
nerus-1.7.0.dist-info/WHEEL
nerus-1.7.0.dist-info/top_level.txt
nerus-1.7.0.dist-info/RECORD
