Metadata-Version: 2.1
Name: nerus
Version: 1.7.0
Summary: Large silver standart Russian corpus with NER, morphology and syntax markup
Home-page: https://github.com/natasha/nerus
Author: Alexander Kukushkin
Author-email: alex@alexkuk.ru
License: MIT
Keywords: russian,nlp,datasets,ner,morphology,syntax
Platform: UNKNOWN
Classifier: License :: OSI Approved :: MIT License
Classifier: Programming Language :: Python :: 3
